{
  "type": "nix:otherworld_type",
  "generator": {
    "type": "minecraft:noise",
    "seed": 0,
    "biome_source": {
      "type": "minecraft:multi_noise",
      "seed": 0,
      "altitude_noise": {
        "firstOctave": -7,
        "amplitudes": [
          1,
          1
        ]
      },
      "temperature_noise": {
        "firstOctave": -7,
        "amplitudes": [
          1,
          1
        ]
      },
      "humidity_noise": {
        "firstOctave": -7,
        "amplitudes": [
          1,
          1
        ]
      },
      "weirdness_noise": {
        "firstOctave": -7,
        "amplitudes": [
          1,
          1
        ]
      },
      "biomes": [
        {
          "biome": "nix:skyforest",
          "parameters": {
            "altitude": 0,
            "temperature": 0,
            "humidity": 0,
            "weirdness": 0,
            "offset": 0
          }
        },
        {
          "biome": "nix:goldforest",
          "parameters": {
            "altitude": 1,
            "temperature": -0.1,
            "humidity": 0,
            "weirdness": 0,
            "offset": 0
          }
        }
      ]
    },
    "settings": {
      "name": "minecraft:floating_islands",
      "bedrock_roof_position": -10,
      "bedrock_floor_position": -10,
      "sea_level": 0,
      "disable_mob_generation": false,
      "default_block": {
        "Name": "nix:godstone"
      },
      "default_fluid": {
        "Name": "minecraft:water",
        "Properties": {
          "level": "0"
        }
      },
      "noise": {
        "height": 128,
        "density_factor": 0,
        "density_offset": 0,
        "size_horizontal": 2,
        "size_vertical": 1,
        "simplex_surface_noise": true,
        "random_density_offset": false,
        "island_noise_override": false,
        "sampling": {
          "xz_scale": 2,
          "y_scale": 1,
          "xz_factor": 80,
          "y_factor": 160
        },
        "bottom_slide": {
          "target": -30,
          "size": 7,
          "offset": 1
        },
        "top_slide": {
          "target": -1000,
          "size": 64,
          "offset": -50
        }
      },
      "structures": {
        "structures": {}
      }
    }
  }
}